powerbirefreshmanual/__init__.py
powerbirefreshmanual/powerbirefreshmanual.py
powerbirefreshmanual-0.0.1.dist-info/LICENSE
powerbirefreshmanual-0.0.1.dist-info/METADATA
powerbirefreshmanual-0.0.1.dist-info/WHEEL
powerbirefreshmanual-0.0.1.dist-info/entry_points.txt
powerbirefreshmanual-0.0.1.dist-info/top_level.txt
powerbirefreshmanual-0.0.1.dist-info/RECORD
