Metadata-Version: 2.1
Name: powerbirefreshmanual
Version: 0.0.1
Summary: Script for refreshing manual Power BI workbooks
Home-page: https://github.com/jor3stuar1/powerbirefreshmanual
Author: Jorge Alvarez
Author-email: jor3stuar1@gmail.com
License: apache2.0
Platform: UNKNOWN
Requires-Dist: pywinauto
Requires-Dist: psutil
